<annotation>
	<folder>JPEGImages</folder>
	<filename>with_mask_312.jpg</filename>
	<path>/Users/oscar/Documents/repositories/mask-detection/JPEGImages/with_mask_312.jpg</path>
	<source>
		<database>Unknown</database>
	</source>
	<size>
		<width>117</width>
		<height>198</height>
		<depth>3</depth>
	</size>
	<segmented>0</segmented>
	<object>
		<name>mask</name>
		<pose>Unspecified</pose>
		<truncated>0</truncated>
		<difficult>0</difficult>
		<bndbox>
			<xmin>20</xmin>
			<ymin>88</ymin>
			<xmax>116</xmax>
			<ymax>190</ymax>
		</bndbox>
	</object>
</annotation>
